intersectioncalc/README.MD
intersectioncalc/__init__.py
intersectioncalc/requirements.txt
intersectioncalc/thirdparty.json
intersectioncalc-0.10.dist-info/LICENSE.rst
intersectioncalc-0.10.dist-info/METADATA
intersectioncalc-0.10.dist-info/WHEEL
intersectioncalc-0.10.dist-info/top_level.txt
intersectioncalc-0.10.dist-info/RECORD
